aiteamwork/__init__.py
aiteamwork/agents/llm_agent.py
aiteamwork/agents/llm_agent_team.py
aiteamwork/callbacks/artifact_verification.py
aiteamwork/callbacks/human_in_the_loop.py
aiteamwork/callbacks/instructions.py
aiteamwork/callbacks/memory.py
aiteamwork/callbacks/pipe.py
aiteamwork/callbacks/stop_when.py
aiteamwork/callbacks/streaming.py
aiteamwork/callbacks/tools_factory.py
aiteamwork/callbacks/trigger_when.py
aiteamwork/callbacks/trimming.py
aiteamwork/contextvar.py
aiteamwork/exceptions/invalid_artifact_exception.py
aiteamwork/exceptions/llm_exception.py
aiteamwork/exceptions/llm_runtime_exception.py
aiteamwork/exceptions/llm_tool_call_failed_exception.py
aiteamwork/llm_agent_content_with_artifact.py
aiteamwork/llm_agent_like.py
aiteamwork/llm_agent_usage.py
aiteamwork/llm_agent_with_dependents.py
aiteamwork/llm_artifact_validator.py
aiteamwork/llm_context.py
aiteamwork/llm_file.py
aiteamwork/llm_file_converter.py
aiteamwork/llm_file_uploader.py
aiteamwork/llm_manifold_pipe.py
aiteamwork/llm_message.py
aiteamwork/llm_pipe.py
aiteamwork/llm_pipeable.py
aiteamwork/llm_prompt_result.py
aiteamwork/llm_prompt_round_result.py
aiteamwork/llm_provider.py
aiteamwork/llm_provider_result.py
aiteamwork/llm_role.py
aiteamwork/llm_serializer.py
aiteamwork/llm_tool_call_request.py
aiteamwork/llm_tool_call_result.py
aiteamwork/llm_tool_executor.py
aiteamwork/llm_tool_flow_control.py
aiteamwork/llm_tool_function.py
aiteamwork/policies/custom_provider_policy.py
aiteamwork/policies/provider_policy.py
aiteamwork/policies/round_robin_provider_policy.py
aiteamwork/policies/switch_when_files_exist_provider_policy.py
aiteamwork/policies/switch_when_token_count_provider_policy.py
aiteamwork/providers/__init__.py
aiteamwork/providers/openai.py
aiteamwork/py.typed
aiteamwork/serializable_producer.py
aiteamwork/tools/agent_team/switch_agent.py
aiteamwork/util/callable.py
aiteamwork/util/date.py
aiteamwork/util/model.py
aiteamwork/util/openapi.py
aiteamwork/util/service_version.py
aiteamwork-0.23.0.dist-info/LICENSE
aiteamwork-0.23.0.dist-info/METADATA
aiteamwork-0.23.0.dist-info/WHEEL
aiteamwork-0.23.0.dist-info/RECORD
